blocky/__init__.py
blocky/async_client.py
blocky/client.py
blocky/exceptions.py
blocky/py.typed
blocky/types.py
blocky/utils.py
blocky/ws_client.py
blockypy-0.2.5.dist-info/METADATA
blockypy-0.2.5.dist-info/WHEEL
blockypy-0.2.5.dist-info/licenses/LICENSE
blockypy-0.2.5.dist-info/RECORD
