Metadata-Version: 2.4
Name: blockypy
Version: 0.2.5
Summary: Official Python client library for the Blocky Crypto Exchange API
Project-URL: Homepage, https://blocky.com.br
Project-URL: Documentation, https://docs.blocky.com.br
Project-URL: Repository, https://github.com/blocky/blockypy
Project-URL: Issues, https://github.com/blocky/blockypy/issues
Author-email: Blocky <support@blocky.com.br>
License-Expression: MIT
License-File: LICENSE
Keywords: api,bitcoin,blocky,crypto,cryptocurrency,exchange,trading
Classifier: Development Status :: 4 - Beta
Classifier: Intended Audience :: Developers
Classifier: Intended Audience :: Financial and Insurance Industry
Classifier: License :: OSI Approved :: MIT License
Classifier: Operating System :: OS Independent
Classifier: Programming Language :: Python :: 3
Classifier: Programming Language :: Python :: 3.8
Classifier: Programming Language :: Python :: 3.9
Classifier: Programming Language :: Python :: 3.10
Classifier: Programming Language :: Python :: 3.11
Classifier: Programming Language :: Python :: 3.12
Classifier: Topic :: Office/Business :: Financial
Classifier: Topic :: Software Development :: Libraries :: Python Modules
Classifier: Typing :: Typed
Requires-Python: >=3.8
Requires-Dist: requests>=2.25.0
Provides-Extra: all
Requires-Dist: httpx>=0.23.0; extra == 'all'
Requires-Dist: mypy>=1.0.0; extra == 'all'
Requires-Dist: pytest-asyncio>=0.21.0; extra == 'all'
Requires-Dist: pytest>=7.0.0; extra == 'all'
Requires-Dist: ruff>=0.1.0; extra == 'all'
Requires-Dist: websockets>=10.0; extra == 'all'
Provides-Extra: async
Requires-Dist: httpx>=0.23.0; extra == 'async'
Provides-Extra: dev
Requires-Dist: httpx>=0.23.0; extra == 'dev'
Requires-Dist: mypy>=1.0.0; extra == 'dev'
Requires-Dist: pytest-asyncio>=0.21.0; extra == 'dev'
Requires-Dist: pytest>=7.0.0; extra == 'dev'
Requires-Dist: ruff>=0.1.0; extra == 'dev'
Requires-Dist: websockets>=10.0; extra == 'dev'
Provides-Extra: ws
Requires-Dist: websockets>=10.0; extra == 'ws'
